{
  "type": "FeatureCollection",
  "features": [
    {
      "type": "Feature",
      "properties": {
        "name": "2025-04-11_05.56.32-trekking.gpx",
        "type": "track"
      },
      "geometry": {
        "type": "LineString",
        "coordinates": [
          [
            7.10043,
            46.476425,
            1557.2
          ],
          [
            7.100393,
            46.476425,
            1557.2
          ],
          [
            7.100357,
            46.476432,
            1557.2
          ],
          [
            7.100333,
            46.47644,
            1557.6
          ],
          [
            7.100312,
            46.476463,
            1557.8
          ],
          [
            7.100295,
            46.476485,
            1558.2
          ],
          [
            7.100278,
            46.476505,
            1558.4
          ],
          [
            7.100263,
            46.47652,
            1558.8
          ],
          [
            7.10024,
            46.476543,
            1559.2
          ],
          [
            7.100227,
            46.47656,
            1559.8
          ],
          [
            7.100198,
            46.476578,
            1560.4
          ],
          [
            7.100177,
            46.476592,
            1561.2
          ],
          [
            7.100157,
            46.47661,
            1561.8
          ],
          [
            7.100145,
            46.476633,
            1562.4
          ],
          [
            7.100135,
            46.476658,
            1563.0
          ],
          [
            7.100115,
            46.476672,
            1563.6
          ],
          [
            7.10011,
            46.47669,
            1564.2
          ],
          [
            7.100105,
            46.47671,
            1564.4
          ],
          [
            7.100093,
            46.476732,
            1565.0
          ],
          [
            7.100073,
            46.476752,
            1565.6
          ],
          [
            7.100072,
            46.47677,
            1566.0
          ],
          [
            7.100058,
            46.47679,
            1566.4
          ],
          [
            7.100042,
            46.476808,
            1567.0
          ],
          [
            7.100028,
            46.476828,
            1567.6
          ],
          [
            7.100015,
            46.476847,
            1568.2
          ],
          [
            7.1,
            46.476863,
            1569.2
          ],
          [
            7.099997,
            46.476885,
            1569.8
          ],
          [
            7.099993,
            46.476905,
            1570.4
          ],
          [
            7.099995,
            46.476923,
            1571.0
          ],
          [
            7.100003,
            46.476943,
            1571.4
          ],
          [
            7.100012,
            46.476962,
            1571.8
          ],
          [
            7.100008,
            46.476982,
            1572.4
          ],
          [
            7.100017,
            46.477003,
            1573.2
          ],
          [
            7.099998,
            46.477017,
            1574.2
          ],
          [
            7.100017,
            46.47704,
            1575.0
          ],
          [
            7.100018,
            46.477058,
            1575.8
          ],
          [
            7.10004,
            46.477083,
            1576.4
          ],
          [
            7.100073,
            46.477087,
            1577.2
          ],
          [
            7.100098,
            46.477097,
            1577.8
          ],
          [
            7.10013,
            46.477097,
            1578.4
          ],
          [
            7.10016,
            46.47709,
            1578.8
          ],
          [
            7.100187,
            46.47708,
            1579.2
          ],
          [
            7.100213,
            46.477075,
            1579.6
          ],
          [
            7.100238,
            46.477062,
            1580.0
          ],
          [
            7.10026,
            46.477048,
            1580.4
          ],
          [
            7.100283,
            46.47704,
            1580.8
          ],
          [
            7.1003,
            46.477023,
            1581.2
          ],
          [
            7.100322,
            46.477007,
            1581.6
          ],
          [
            7.100348,
            46.476998,
            1581.8
          ],
          [
            7.100375,
            46.476988,
            1582.0
          ],
          [
            7.100405,
            46.476982,
            1582.4
          ],
          [
            7.10044,
            46.476968,
            1582.8
          ],
          [
            7.100465,
            46.47696,
            1583.2
          ],
          [
            7.100487,
            46.476943,
            1583.6
          ],
          [
            7.100513,
            46.476937,
            1584.4
          ],
          [
            7.100542,
            46.47694,
            1584.6
          ],
          [
            7.100577,
            46.47694,
            1585.2
          ],
          [
            7.100602,
            46.47694,
            1585.6
          ],
          [
            7.100632,
            46.476943,
            1586.0
          ],
          [
            7.100668,
            46.47694,
            1586.6
          ],
          [
            7.1007,
            46.476943,
            1587.2
          ],
          [
            7.100723,
            46.476957,
            1588.0
          ],
          [
            7.100748,
            46.476978,
            1588.8
          ],
          [
            7.100752,
            46.476998,
            1589.4
          ],
          [
            7.100748,
            46.477017,
            1589.8
          ],
          [
            7.100728,
            46.47703,
            1590.2
          ],
          [
            7.100708,
            46.477045,
            1590.8
          ],
          [
            7.100688,
            46.477062,
            1591.2
          ],
          [
            7.100678,
            46.47708,
            1591.6
          ],
          [
            7.100663,
            46.4771,
            1592.4
          ],
          [
            7.100652,
            46.47712,
            1592.8
          ],
          [
            7.100657,
            46.477138,
            1593.4
          ],
          [
            7.10066,
            46.477158,
            1594.2
          ],
          [
            7.100638,
            46.477177,
            1595.0
          ],
          [
            7.100645,
            46.477202,
            1595.8
          ],
          [
            7.10066,
            46.477218,
            1596.2
          ],
          [
            7.100693,
            46.477218,
            1597.2
          ],
          [
            7.10072,
            46.477218,
            1597.8
          ],
          [
            7.100748,
            46.477225,
            1598.2
          ],
          [
            7.100777,
            46.477215,
            1598.6
          ],
          [
            7.100797,
            46.4772,
            1600.0
          ],
          [
            7.100833,
            46.477197,
            1600.6
          ],
          [
            7.10086,
            46.47719,
            1601.2
          ],
          [
            7.100895,
            46.477187,
            1601.8
          ],
          [
            7.10092,
            46.477187,
            1602.2
          ],
          [
            7.100947,
            46.477177,
            1602.8
          ],
          [
            7.100975,
            46.477167,
            1603.4
          ],
          [
            7.100995,
            46.477148,
            1604.0
          ],
          [
            7.101025,
            46.477142,
            1604.8
          ],
          [
            7.10106,
            46.477142,
            1605.4
          ],
          [
            7.101093,
            46.477135,
            1606.0
          ],
          [
            7.10113,
            46.477128,
            1606.6
          ],
          [
            7.101158,
            46.477128,
            1607.2
          ],
          [
            7.101195,
            46.477138,
            1607.8
          ],
          [
            7.101222,
            46.477135,
            1608.2
          ],
          [
            7.10125,
            46.477148,
            1608.8
          ],
          [
            7.101277,
            46.477142,
            1609.2
          ],
          [
            7.101318,
            46.477158,
            1609.8
          ],
          [
            7.101342,
            46.477177,
            1610.6
          ],
          [
            7.101348,
            46.477202,
            1611.2
          ],
          [
            7.10134,
            46.477222,
            1611.4
          ],
          [
            7.101327,
            46.47724,
            1611.8
          ],
          [
            7.101308,
            46.477253,
            1612.2
          ],
          [
            7.101277,
            46.477263,
            1612.8
          ],
          [
            7.101253,
            46.477282,
            1613.4
          ],
          [
            7.10123,
            46.477295,
            1614.2
          ],
          [
            7.10121,
            46.477318,
            1615.0
          ],
          [
            7.101193,
            46.477337,
            1615.6
          ],
          [
            7.101175,
            46.477357,
            1616.2
          ],
          [
            7.101165,
            46.477375,
            1616.6
          ],
          [
            7.101157,
            46.477398,
            1617.2
          ],
          [
            7.101153,
            46.477417,
            1617.8
          ],
          [
            7.101138,
            46.47744,
            1618.6
          ],
          [
            7.101123,
            46.477458,
            1619.0
          ],
          [
            7.101113,
            46.477483,
            1619.6
          ],
          [
            7.101108,
            46.477503,
            1620.0
          ],
          [
            7.101098,
            46.477525,
            1620.8
          ],
          [
            7.101098,
            46.477552,
            1621.4
          ],
          [
            7.101105,
            46.477573,
            1622.2
          ],
          [
            7.101133,
            46.477587,
            1623.0
          ],
          [
            7.101163,
            46.477602,
            1623.6
          ],
          [
            7.10119,
            46.477587,
            1624.2
          ],
          [
            7.10121,
            46.477573,
            1624.6
          ],
          [
            7.10123,
            46.477558,
            1624.8
          ],
          [
            7.101257,
            46.477538,
            1625.0
          ],
          [
            7.101287,
            46.477532,
            1625.4
          ],
          [
            7.101312,
            46.477522,
            1625.8
          ],
          [
            7.101345,
            46.477522,
            1626.2
          ],
          [
            7.101382,
            46.477532,
            1626.6
          ],
          [
            7.101408,
            46.477522,
            1626.8
          ],
          [
            7.101442,
            46.477517,
            1627.4
          ],
          [
            7.101473,
            46.477517,
            1628.0
          ],
          [
            7.10151,
            46.47752,
            1628.8
          ],
          [
            7.101545,
            46.47752,
            1629.2
          ],
          [
            7.101578,
            46.477522,
            1630.0
          ],
          [
            7.101612,
            46.477535,
            1630.8
          ],
          [
            7.101638,
            46.477535,
            1631.4
          ],
          [
            7.101675,
            46.477535,
            1632.2
          ],
          [
            7.101705,
            46.477545,
            1632.8
          ],
          [
            7.101728,
            46.477555,
            1633.2
          ],
          [
            7.10176,
            46.47756,
            1634.0
          ],
          [
            7.101783,
            46.477573,
            1634.4
          ],
          [
            7.101808,
            46.477567,
            1635.0
          ],
          [
            7.101833,
            46.477577,
            1635.6
          ],
          [
            7.101867,
            46.47758,
            1636.4
          ],
          [
            7.101887,
            46.477593,
            1636.8
          ],
          [
            7.101882,
            46.477612,
            1637.2
          ],
          [
            7.10187,
            46.477632,
            1637.6
          ],
          [
            7.101855,
            46.47765,
            1637.8
          ],
          [
            7.101833,
            46.477663,
            1638.2
          ],
          [
            7.101815,
            46.477682,
            1638.8
          ],
          [
            7.101788,
            46.477698,
            1639.4
          ],
          [
            7.101768,
            46.477712,
            1640.0
          ],
          [
            7.101745,
            46.477737,
            1641.0
          ],
          [
            7.101735,
            46.47776,
            1641.8
          ],
          [
            7.10172,
            46.477782,
            1642.4
          ],
          [
            7.101702,
            46.47781,
            1643.2
          ],
          [
            7.101685,
            46.477837,
            1643.8
          ],
          [
            7.101672,
            46.477858,
            1644.4
          ],
          [
            7.10166,
            46.477878,
            1645.2
          ],
          [
            7.101643,
            46.477897,
            1645.8
          ],
          [
            7.101633,
            46.47792,
            1646.4
          ],
          [
            7.101618,
            46.477942,
            1647.2
          ],
          [
            7.101595,
            46.47797,
            1647.6
          ],
          [
            7.101582,
            46.477997,
            1648.2
          ],
          [
            7.101577,
            46.478015,
            1648.6
          ],
          [
            7.101562,
            46.478032,
            1648.8
          ],
          [
            7.101547,
            46.478053,
            1649.4
          ],
          [
            7.10154,
            46.478073,
            1650.0
          ],
          [
            7.101522,
            46.478095,
            1650.8
          ],
          [
            7.101513,
            46.478115,
            1651.2
          ],
          [
            7.101503,
            46.47814,
            1651.6
          ],
          [
            7.101497,
            46.47816,
            1652.2
          ],
          [
            7.101493,
            46.478178,
            1652.8
          ],
          [
            7.10149,
            46.4782,
            1653.4
          ],
          [
            7.10149,
            46.47822,
            1654.0
          ],
          [
            7.101493,
            46.478242,
            1654.6
          ],
          [
            7.1015,
            46.478262,
            1655.2
          ],
          [
            7.101503,
            46.47828,
            1655.6
          ],
          [
            7.101505,
            46.478313,
            1656.6
          ],
          [
            7.101517,
            46.478338,
            1657.6
          ],
          [
            7.10154,
            46.478367,
            1658.2
          ],
          [
            7.10158,
            46.47838,
            1658.6
          ],
          [
            7.101617,
            46.478373,
            1659.2
          ],
          [
            7.101638,
            46.478358,
            1659.8
          ],
          [
            7.101662,
            46.478338,
            1660.4
          ],
          [
            7.101695,
            46.478325,
            1661.0
          ],
          [
            7.101723,
            46.478307,
            1661.6
          ],
          [
            7.101748,
            46.478287,
            1662.0
          ],
          [
            7.10178,
            46.478272,
            1662.6
          ],
          [
            7.101813,
            46.478258,
            1663.2
          ],
          [
            7.101843,
            46.478242,
            1663.8
          ],
          [
            7.101873,
            46.47823,
            1664.4
          ],
          [
            7.101902,
            46.478213,
            1664.8
          ],
          [
            7.101935,
            46.478198,
            1665.2
          ],
          [
            7.101967,
            46.478195,
            1665.8
          ],
          [
            7.102002,
            46.478188,
            1666.4
          ],
          [
            7.102038,
            46.478182,
            1667.0
          ],
          [
            7.102072,
            46.478178,
            1667.6
          ],
          [
            7.102103,
            46.478175,
            1668.2
          ],
          [
            7.102138,
            46.478168,
            1668.8
          ],
          [
            7.102172,
            46.478162,
            1669.4
          ],
          [
            7.102202,
            46.47816,
            1670.0
          ],
          [
            7.102235,
            46.47816,
            1670.6
          ],
          [
            7.10226,
            46.478157,
            1671.0
          ],
          [
            7.102293,
            46.478157,
            1671.6
          ],
          [
            7.102323,
            46.478153,
            1672.4
          ],
          [
            7.102352,
            46.478157,
            1673.0
          ],
          [
            7.10238,
            46.478157,
            1673.6
          ],
          [
            7.102412,
            46.478157,
            1674.2
          ],
          [
            7.102443,
            46.47816,
            1674.6
          ],
          [
            7.102473,
            46.47816,
            1675.2
          ],
          [
            7.102502,
            46.47816,
            1675.8
          ],
          [
            7.102537,
            46.47816,
            1676.4
          ],
          [
            7.102567,
            46.478162,
            1677.0
          ],
          [
            7.1026,
            46.478162,
            1677.6
          ],
          [
            7.10263,
            46.478168,
            1678.2
          ],
          [
            7.102663,
            46.478162,
            1678.8
          ],
          [
            7.102698,
            46.478168,
            1679.2
          ],
          [
            7.102723,
            46.478172,
            1679.8
          ],
          [
            7.102755,
            46.478175,
            1680.6
          ],
          [
            7.102782,
            46.478175,
            1681.2
          ],
          [
            7.102817,
            46.478175,
            1681.8
          ],
          [
            7.102848,
            46.478178,
            1682.4
          ],
          [
            7.10288,
            46.478188,
            1683.0
          ],
          [
            7.10291,
            46.478195,
            1683.8
          ],
          [
            7.102943,
            46.478195,
            1684.2
          ],
          [
            7.10298,
            46.478195,
            1684.8
          ],
          [
            7.103012,
            46.478195,
            1685.4
          ],
          [
            7.103043,
            46.478195,
            1686.0
          ],
          [
            7.10308,
            46.478192,
            1686.4
          ],
          [
            7.103112,
            46.478195,
            1687.0
          ],
          [
            7.103152,
            46.478195,
            1687.6
          ],
          [
            7.103188,
            46.4782,
            1688.2
          ],
          [
            7.103225,
            46.478207,
            1688.8
          ],
          [
            7.103258,
            46.478207,
            1689.2
          ],
          [
            7.103293,
            46.4782,
            1689.8
          ],
          [
            7.103323,
            46.4782,
            1690.2
          ],
          [
            7.10336,
            46.478207,
            1690.6
          ],
          [
            7.103393,
            46.478213,
            1691.2
          ],
          [
            7.103428,
            46.478217,
            1691.8
          ],
          [
            7.103468,
            46.478217,
            1692.2
          ],
          [
            7.1035,
            46.478227,
            1692.8
          ],
          [
            7.103528,
            46.47822,
            1693.4
          ],
          [
            7.10356,
            46.47823,
            1693.8
          ],
          [
            7.103593,
            46.478237,
            1694.2
          ],
          [
            7.103635,
            46.47824,
            1694.8
          ],
          [
            7.103665,
            46.47824,
            1695.4
          ],
          [
            7.1037,
            46.47824,
            1695.8
          ],
          [
            7.10374,
            46.478242,
            1696.4
          ],
          [
            7.103777,
            46.478248,
            1697.0
          ],
          [
            7.103808,
            46.478248,
            1697.6
          ],
          [
            7.103843,
            46.478252,
            1698.2
          ],
          [
            7.103883,
            46.478258,
            1698.6
          ],
          [
            7.103918,
            46.478262,
            1699.2
          ],
          [
            7.10395,
            46.478268,
            1699.6
          ],
          [
            7.103985,
            46.478268,
            1700.0
          ],
          [
            7.10402,
            46.478268,
            1700.4
          ],
          [
            7.104062,
            46.478272,
            1701.2
          ],
          [
            7.104092,
            46.478275,
            1701.6
          ],
          [
            7.104123,
            46.478278,
            1702.0
          ],
          [
            7.104163,
            46.47828,
            1702.6
          ],
          [
            7.104198,
            46.47829,
            1703.2
          ],
          [
            7.104233,
            46.478293,
            1703.8
          ],
          [
            7.104272,
            46.478297,
            1704.4
          ],
          [
            7.10431,
            46.478307,
            1705.0
          ],
          [
            7.10434,
            46.478313,
            1705.4
          ],
          [
            7.104367,
            46.478317,
            1706.0
          ],
          [
            7.104402,
            46.478325,
            1706.8
          ],
          [
            7.104438,
            46.478332,
            1707.2
          ],
          [
            7.104465,
            46.478338,
            1707.8
          ],
          [
            7.104495,
            46.478342,
            1708.2
          ],
          [
            7.104522,
            46.478348,
            1708.8
          ],
          [
            7.104552,
            46.478355,
            1709.4
          ],
          [
            7.104582,
            46.478358,
            1710.0
          ],
          [
            7.104612,
            46.478367,
            1710.6
          ],
          [
            7.10464,
            46.478373,
            1711.2
          ],
          [
            7.10467,
            46.478387,
            1711.6
          ],
          [
            7.1047,
            46.478393,
            1712.2
          ],
          [
            7.10473,
            46.478405,
            1712.6
          ],
          [
            7.104758,
            46.478408,
            1713.2
          ],
          [
            7.104783,
            46.478415,
            1713.8
          ],
          [
            7.104817,
            46.478428,
            1714.2
          ],
          [
            7.104845,
            46.478435,
            1714.8
          ],
          [
            7.104877,
            46.47845,
            1715.6
          ],
          [
            7.104902,
            46.47846,
            1716.4
          ],
          [
            7.104925,
            46.47848,
            1717.0
          ],
          [
            7.104948,
            46.478495,
            1717.4
          ],
          [
            7.104955,
            46.478518,
            1717.8
          ],
          [
            7.104948,
            46.47854,
            1718.4
          ],
          [
            7.104925,
            46.47856,
            1719.0
          ],
          [
            7.104902,
            46.478575,
            1720.2
          ],
          [
            7.104903,
            46.478603,
            1721.0
          ],
          [
            7.104912,
            46.47863,
            1721.6
          ],
          [
            7.104925,
            46.478655,
            1722.6
          ],
          [
            7.104928,
            46.478678,
            1723.4
          ],
          [
            7.104933,
            46.478697,
            1724.0
          ],
          [
            7.10494,
            46.478722,
            1724.6
          ],
          [
            7.104948,
            46.478748,
            1725.4
          ],
          [
            7.104955,
            46.47877,
            1726.0
          ],
          [
            7.104955,
            46.47879,
            1726.4
          ],
          [
            7.104958,
            46.478808,
            1727.0
          ],
          [
            7.10496,
            46.478828,
            1727.6
          ],
          [
            7.104962,
            46.47885,
            1728.0
          ],
          [
            7.10496,
            46.47887,
            1729.0
          ],
          [
            7.10496,
            46.478888,
            1729.6
          ],
          [
            7.104955,
            46.478918,
            1730.6
          ],
          [
            7.104955,
            46.478937,
            1731.2
          ],
          [
            7.104955,
            46.478957,
            1731.8
          ],
          [
            7.10496,
            46.478982,
            1732.6
          ],
          [
            7.10496,
            46.479003,
            1733.4
          ],
          [
            7.10496,
            46.479027,
            1734.2
          ],
          [
            7.104962,
            46.479045,
            1734.8
          ],
          [
            7.104962,
            46.479065,
            1735.4
          ],
          [
            7.104965,
            46.479087,
            1736.2
          ],
          [
            7.104968,
            46.479107,
            1737.2
          ],
          [
            7.104972,
            46.479125,
            1737.8
          ],
          [
            7.104977,
            46.479145,
            1738.4
          ],
          [
            7.104977,
            46.479163,
            1739.0
          ],
          [
            7.104975,
            46.479187,
            1739.6
          ],
          [
            7.104975,
            46.479208,
            1740.6
          ],
          [
            7.10498,
            46.479228,
            1741.2
          ],
          [
            7.104982,
            46.47925,
            1741.6
          ],
          [
            7.104982,
            46.479273,
            1742.4
          ],
          [
            7.10498,
            46.479292,
            1743.0
          ],
          [
            7.104982,
            46.479315,
            1743.6
          ],
          [
            7.10498,
            46.479333,
            1744.0
          ],
          [
            7.104985,
            46.479353,
            1744.4
          ],
          [
            7.104982,
            46.479372,
            1744.8
          ],
          [
            7.104982,
            46.479392,
            1745.4
          ],
          [
            7.104982,
            46.47941,
            1745.8
          ],
          [
            7.104978,
            46.47943,
            1746.2
          ],
          [
            7.104977,
            46.479448,
            1746.8
          ],
          [
            7.104978,
            46.479472,
            1747.0
          ],
          [
            7.10498,
            46.479497,
            1747.4
          ],
          [
            7.10498,
            46.479525,
            1748.6
          ],
          [
            7.104977,
            46.479552,
            1749.2
          ],
          [
            7.104972,
            46.47957,
            1749.8
          ],
          [
            7.104962,
            46.479593,
            1750.4
          ],
          [
            7.104953,
            46.479612,
            1750.8
          ],
          [
            7.104945,
            46.479632,
            1751.6
          ],
          [
            7.104943,
            46.47965,
            1752.0
          ],
          [
            7.104938,
            46.479677,
            1752.6
          ],
          [
            7.104933,
            46.479698,
            1753.0
          ],
          [
            7.104932,
            46.479718,
            1753.6
          ],
          [
            7.104932,
            46.479737,
            1754.2
          ],
          [
            7.104932,
            46.479757,
            1754.6
          ],
          [
            7.104933,
            46.479775,
            1755.2
          ],
          [
            7.104933,
            46.479798,
            1755.8
          ],
          [
            7.104928,
            46.479817,
            1756.2
          ],
          [
            7.104925,
            46.479842,
            1756.8
          ],
          [
            7.104928,
            46.479865,
            1757.2
          ],
          [
            7.104925,
            46.479883,
            1757.8
          ],
          [
            7.104928,
            46.479903,
            1758.4
          ],
          [
            7.104928,
            46.479922,
            1758.6
          ],
          [
            7.104928,
            46.479945,
            1759.2
          ],
          [
            7.104928,
            46.479963,
            1759.6
          ],
          [
            7.104923,
            46.479987,
            1760.2
          ],
          [
            7.104923,
            46.480005,
            1760.6
          ],
          [
            7.104923,
            46.480028,
            1761.2
          ],
          [
            7.104925,
            46.480057,
            1761.8
          ],
          [
            7.104928,
            46.480077,
            1762.4
          ],
          [
            7.104932,
            46.480095,
            1762.8
          ],
          [
            7.104938,
            46.480118,
            1763.4
          ],
          [
            7.10494,
            46.48014,
            1764.0
          ],
          [
            7.104943,
            46.480162,
            1764.6
          ],
          [
            7.104948,
            46.480185,
            1765.2
          ],
          [
            7.104948,
            46.480207,
            1765.6
          ],
          [
            7.104948,
            46.480227,
            1766.2
          ],
          [
            7.104955,
            46.480252,
            1766.6
          ],
          [
            7.104957,
            46.480278,
            1767.2
          ],
          [
            7.104958,
            46.480297,
            1767.8
          ],
          [
            7.10496,
            46.480317,
            1768.4
          ],
          [
            7.10496,
            46.480335,
            1769.0
          ],
          [
            7.10496,
            46.480358,
            1769.4
          ],
          [
            7.104948,
            46.48038,
            1770.0
          ],
          [
            7.10494,
            46.480402,
            1770.6
          ],
          [
            7.104938,
            46.480432,
            1771.0
          ],
          [
            7.10494,
            46.480453,
            1771.6
          ],
          [
            7.104942,
            46.480477,
            1772.0
          ],
          [
            7.104942,
            46.480502,
            1772.4
          ],
          [
            7.104938,
            46.48052,
            1773.0
          ],
          [
            7.104937,
            46.480543,
            1773.6
          ],
          [
            7.104938,
            46.480562,
            1774.2
          ],
          [
            7.104935,
            46.480585,
            1774.8
          ],
          [
            7.104932,
            46.480603,
            1775.2
          ],
          [
            7.104932,
            46.480623,
            1775.8
          ],
          [
            7.104928,
            46.480648,
            1776.2
          ],
          [
            7.104922,
            46.480672,
            1776.8
          ],
          [
            7.104915,
            46.480693,
            1777.6
          ],
          [
            7.104908,
            46.480713,
            1778.2
          ],
          [
            7.104898,
            46.480732,
            1778.8
          ],
          [
            7.104895,
            46.480755,
            1779.0
          ],
          [
            7.104885,
            46.480777,
            1779.6
          ],
          [
            7.104877,
            46.480797,
            1780.4
          ],
          [
            7.104872,
            46.480815,
            1781.0
          ],
          [
            7.104872,
            46.480835,
            1781.6
          ],
          [
            7.104872,
            46.48086,
            1782.2
          ],
          [
            7.104868,
            46.48088,
            1782.8
          ],
          [
            7.104865,
            46.480908,
            1783.4
          ],
          [
            7.104868,
            46.48093,
            1784.0
          ],
          [
            7.104868,
            46.48095,
            1784.6
          ],
          [
            7.104868,
            46.480972,
            1785.2
          ],
          [
            7.104862,
            46.480995,
            1785.8
          ],
          [
            7.104857,
            46.481013,
            1786.4
          ],
          [
            7.10486,
            46.481033,
            1786.8
          ],
          [
            7.10486,
            46.481055,
            1787.4
          ],
          [
            7.104857,
            46.481075,
            1788.0
          ],
          [
            7.104857,
            46.481093,
            1788.6
          ],
          [
            7.104855,
            46.481117,
            1789.2
          ],
          [
            7.104847,
            46.481138,
            1789.6
          ],
          [
            7.10484,
            46.481158,
            1790.2
          ],
          [
            7.104838,
            46.481177,
            1790.8
          ],
          [
            7.104832,
            46.481205,
            1791.8
          ],
          [
            7.104823,
            46.481225,
            1792.2
          ],
          [
            7.104817,
            46.481247,
            1793.0
          ],
          [
            7.104812,
            46.48127,
            1793.8
          ],
          [
            7.104803,
            46.481288,
            1794.8
          ],
          [
            7.1048,
            46.481312,
            1795.6
          ],
          [
            7.104798,
            46.481333,
            1796.2
          ],
          [
            7.104798,
            46.481357,
            1796.8
          ],
          [
            7.104793,
            46.481375,
            1797.4
          ],
          [
            7.104782,
            46.481403,
            1798.0
          ],
          [
            7.104778,
            46.481423,
            1798.6
          ],
          [
            7.104758,
            46.481445,
            1799.2
          ],
          [
            7.10474,
            46.481468,
            1800.2
          ],
          [
            7.10473,
            46.481493,
            1801.2
          ],
          [
            7.10473,
            46.481513,
            1801.8
          ],
          [
            7.104735,
            46.481535,
            1802.4
          ],
          [
            7.104737,
            46.481555,
            1802.8
          ],
          [
            7.10474,
            46.481577,
            1803.6
          ],
          [
            7.10475,
            46.481597,
            1804.2
          ],
          [
            7.104763,
            46.481612,
            1804.8
          ],
          [
            7.104767,
            46.481638,
            1805.6
          ],
          [
            7.104775,
            46.481663,
            1806.6
          ],
          [
            7.10478,
            46.481682,
            1807.2
          ],
          [
            7.10478,
            46.481705,
            1807.8
          ],
          [
            7.104773,
            46.481723,
            1808.2
          ],
          [
            7.104763,
            46.481747,
            1808.8
          ],
          [
            7.104758,
            46.481772,
            1809.2
          ],
          [
            7.104753,
            46.481792,
            1809.6
          ],
          [
            7.10475,
            46.481813,
            1810.0
          ],
          [
            7.104743,
            46.481837,
            1810.4
          ],
          [
            7.104737,
            46.481862,
            1810.8
          ],
          [
            7.10473,
            46.48188,
            1811.4
          ],
          [
            7.104725,
            46.481907,
            1811.8
          ],
          [
            7.104723,
            46.481928,
            1812.4
          ],
          [
            7.104725,
            46.481952,
            1812.8
          ],
          [
            7.104723,
            46.481973,
            1813.4
          ],
          [
            7.104722,
            46.481993,
            1813.8
          ],
          [
            7.10472,
            46.482012,
            1814.4
          ],
          [
            7.104718,
            46.482035,
            1814.6
          ],
          [
            7.10472,
            46.482053,
            1815.2
          ],
          [
            7.104715,
            46.48208,
            1815.6
          ],
          [
            7.104713,
            46.482102,
            1816.2
          ],
          [
            7.104717,
            46.482123,
            1816.8
          ],
          [
            7.104717,
            46.482147,
            1817.2
          ],
          [
            7.104717,
            46.482168,
            1817.8
          ],
          [
            7.104718,
            46.482192,
            1818.4
          ],
          [
            7.10472,
            46.48221,
            1818.8
          ],
          [
            7.10472,
            46.482233,
            1819.2
          ],
          [
            7.104718,
            46.482262,
            1819.8
          ],
          [
            7.10471,
            46.482283,
            1820.4
          ],
          [
            7.104702,
            46.482307,
            1820.8
          ],
          [
            7.104697,
            46.482325,
            1821.4
          ],
          [
            7.104682,
            46.482348,
            1821.8
          ],
          [
            7.104673,
            46.48237,
            1822.2
          ],
          [
            7.104663,
            46.482393,
            1822.8
          ],
          [
            7.104653,
            46.482418,
            1823.6
          ],
          [
            7.104645,
            46.48244,
            1824.2
          ],
          [
            7.104635,
            46.482463,
            1824.6
          ],
          [
            7.104622,
            46.482485,
            1825.2
          ],
          [
            7.104613,
            46.482508,
            1825.6
          ],
          [
            7.1046,
            46.482527,
            1826.0
          ],
          [
            7.104588,
            46.48255,
            1826.4
          ],
          [
            7.10458,
            46.482578,
            1826.8
          ],
          [
            7.104573,
            46.482603,
            1827.0
          ],
          [
            7.104568,
            46.48263,
            1827.4
          ],
          [
            7.104563,
            46.482662,
            1827.6
          ],
          [
            7.104558,
            46.482687,
            1827.8
          ],
          [
            7.104548,
            46.48271,
            1828.2
          ],
          [
            7.104537,
            46.482738,
            1828.6
          ],
          [
            7.104522,
            46.482755,
            1829.0
          ],
          [
            7.104512,
            46.482777,
            1829.4
          ],
          [
            7.104498,
            46.4828,
            1829.8
          ],
          [
            7.104487,
            46.482825,
            1830.2
          ],
          [
            7.10448,
            46.482847,
            1830.6
          ],
          [
            7.10448,
            46.48288,
            1830.8
          ],
          [
            7.104482,
            46.482902,
            1831.0
          ],
          [
            7.104478,
            46.482923,
            1831.2
          ],
          [
            7.104463,
            46.482943,
            1831.4
          ],
          [
            7.104462,
            46.482965,
            1831.6
          ],
          [
            7.10446,
            46.482988,
            1832.0
          ],
          [
            7.104443,
            46.483013,
            1832.4
          ],
          [
            7.10443,
            46.483033,
            1832.8
          ],
          [
            7.104417,
            46.483052,
            1833.2
          ],
          [
            7.104398,
            46.483078,
            1833.6
          ],
          [
            7.104387,
            46.483097,
            1834.2
          ],
          [
            7.10438,
            46.483117,
            1834.6
          ],
          [
            7.10436,
            46.483135,
            1835.4
          ],
          [
            7.10434,
            46.483152,
            1836.2
          ],
          [
            7.104322,
            46.483163,
            1836.6
          ],
          [
            7.10431,
            46.48318,
            1837.4
          ],
          [
            7.104293,
            46.483202,
            1838.0
          ],
          [
            7.10428,
            46.483218,
            1838.6
          ],
          [
            7.104268,
            46.48324,
            1839.2
          ],
          [
            7.104257,
            46.483257,
            1840.0
          ],
          [
            7.10424,
            46.483277,
            1840.8
          ],
          [
            7.104225,
            46.483298,
            1841.6
          ],
          [
            7.104217,
            46.483318,
            1842.6
          ],
          [
            7.104208,
            46.48334,
            1843.4
          ],
          [
            7.1042,
            46.48336,
            1844.8
          ],
          [
            7.104185,
            46.483375,
            1845.8
          ],
          [
            7.104168,
            46.483392,
            1846.6
          ],
          [
            7.104148,
            46.483403,
            1847.6
          ],
          [
            7.104135,
            46.483423,
            1848.8
          ],
          [
            7.104118,
            46.48344,
            1849.2
          ],
          [
            7.1041,
            46.483455,
            1850.2
          ],
          [
            7.10409,
            46.48348,
            1851.6
          ],
          [
            7.104082,
            46.483503,
            1852.6
          ],
          [
            7.10407,
            46.48352,
            1853.8
          ],
          [
            7.104058,
            46.483535,
            1854.8
          ],
          [
            7.104047,
            46.483555,
            1856.2
          ],
          [
            7.10404,
            46.483573,
            1856.8
          ],
          [
            7.10402,
            46.48359,
            1858.0
          ],
          [
            7.104003,
            46.483608,
            1859.4
          ],
          [
            7.103987,
            46.483628,
            1860.2
          ],
          [
            7.103958,
            46.483638,
            1861.2
          ],
          [
            7.103937,
            46.48365,
            1862.4
          ],
          [
            7.103908,
            46.483663,
            1863.6
          ],
          [
            7.103892,
            46.48368,
            1864.4
          ],
          [
            7.103875,
            46.483698,
            1865.6
          ],
          [
            7.103857,
            46.483712,
            1866.6
          ],
          [
            7.103838,
            46.483727,
            1867.4
          ],
          [
            7.103817,
            46.483743,
            1868.0
          ],
          [
            7.103802,
            46.48376,
            1868.6
          ],
          [
            7.10378,
            46.483772,
            1869.4
          ],
          [
            7.10376,
            46.483788,
            1870.6
          ],
          [
            7.103733,
            46.483807,
            1871.8
          ],
          [
            7.103707,
            46.48382,
            1872.8
          ],
          [
            7.103687,
            46.483833,
            1873.6
          ],
          [
            7.103673,
            46.483848,
            1874.4
          ],
          [
            7.10365,
            46.483858,
            1875.8
          ],
          [
            7.103635,
            46.483875,
            1876.8
          ],
          [
            7.103622,
            46.483893,
            1877.6
          ],
          [
            7.103607,
            46.48391,
            1878.4
          ],
          [
            7.10359,
            46.483925,
            1879.4
          ],
          [
            7.103568,
            46.483938,
            1880.6
          ],
          [
            7.103548,
            46.483955,
            1881.6
          ],
          [
            7.103533,
            46.48397,
            1882.8
          ],
          [
            7.103518,
            46.48399,
            1884.0
          ],
          [
            7.1035,
            46.484005,
            1885.4
          ],
          [
            7.103478,
            46.484018,
            1886.4
          ],
          [
            7.103458,
            46.484032,
            1887.4
          ],
          [
            7.103432,
            46.48404,
            1888.4
          ],
          [
            7.103407,
            46.484057,
            1889.4
          ],
          [
            7.103387,
            46.48407,
            1891.0
          ],
          [
            7.103373,
            46.484095,
            1892.8
          ],
          [
            7.103347,
            46.484108,
            1893.8
          ],
          [
            7.10332,
            46.484115,
            1895.2
          ],
          [
            7.103298,
            46.484127,
            1896.4
          ],
          [
            7.103265,
            46.484133,
            1897.6
          ],
          [
            7.10324,
            46.484147,
            1898.8
          ],
          [
            7.10322,
            46.48416,
            1899.6
          ],
          [
            7.1032,
            46.484172,
            1901.0
          ],
          [
            7.10318,
            46.484185,
            1902.0
          ],
          [
            7.103168,
            46.484203,
            1903.8
          ],
          [
            7.103148,
            46.484223,
            1905.0
          ],
          [
            7.10312,
            46.484233,
            1907.4
          ],
          [
            7.103088,
            46.484237,
            1908.8
          ],
          [
            7.103065,
            46.484252,
            1910.6
          ],
          [
            7.103052,
            46.484272,
            1912.2
          ],
          [
            7.103042,
            46.48429,
            1913.6
          ],
          [
            7.103037,
            46.48431,
            1915.2
          ],
          [
            7.103007,
            46.484313,
            1916.8
          ],
          [
            7.102975,
            46.48432,
            1917.8
          ],
          [
            7.102963,
            46.484338,
            1919.6
          ],
          [
            7.10295,
            46.484363,
            1921.0
          ],
          [
            7.102925,
            46.484377,
            1923.2
          ],
          [
            7.10291,
            46.484393,
            1924.2
          ],
          [
            7.10289,
            46.484405,
            1925.6
          ],
          [
            7.102868,
            46.484418,
            1927.2
          ],
          [
            7.102855,
            46.484435,
            1928.6
          ],
          [
            7.102835,
            46.484447,
            1930.2
          ],
          [
            7.102822,
            46.484467,
            1931.4
          ],
          [
            7.102798,
            46.484477,
            1932.6
          ],
          [
            7.102772,
            46.484473,
            1933.6
          ],
          [
            7.102745,
            46.484482,
            1935.2
          ],
          [
            7.102723,
            46.484495,
            1936.4
          ],
          [
            7.1027,
            46.484502,
            1937.8
          ],
          [
            7.102675,
            46.484512,
            1939.2
          ],
          [
            7.102658,
            46.484527,
            1940.8
          ],
          [
            7.102635,
            46.484537,
            1943.2
          ],
          [
            7.10262,
            46.484553,
            1945.0
          ],
          [
            7.102622,
            46.484572,
            1946.8
          ],
          [
            7.10263,
            46.484592,
            1947.6
          ],
          [
            7.102627,
            46.48461,
            1949.4
          ],
          [
            7.102598,
            46.48461,
            1950.4
          ],
          [
            7.102575,
            46.484623,
            1951.6
          ],
          [
            7.10258,
            46.484642,
            1952.8
          ],
          [
            7.102585,
            46.484662,
            1954.2
          ],
          [
            7.10259,
            46.48468,
            1955.4
          ],
          [
            7.102582,
            46.4847,
            1957.0
          ],
          [
            7.102567,
            46.484717,
            1960.0
          ],
          [
            7.10255,
            46.484732,
            1961.6
          ],
          [
            7.102533,
            46.484748,
            1963.4
          ],
          [
            7.102515,
            46.484763,
            1965.2
          ],
          [
            7.102498,
            46.48478,
            1966.4
          ],
          [
            7.10248,
            46.4848,
            1968.6
          ],
          [
            7.102485,
            46.484822,
            1969.8
          ],
          [
            7.10248,
            46.48484,
            1971.6
          ],
          [
            7.102457,
            46.48485,
            1973.2
          ],
          [
            7.102428,
            46.484853,
            1974.4
          ],
          [
            7.102405,
            46.484863,
            1975.4
          ],
          [
            7.102392,
            46.48488,
            1977.0
          ],
          [
            7.102378,
            46.484898,
            1978.4
          ],
          [
            7.102365,
            46.484915,
            1979.6
          ],
          [
            7.102347,
            46.48493,
            1981.4
          ],
          [
            7.102335,
            46.48495,
            1983.2
          ],
          [
            7.102317,
            46.484965,
            1984.6
          ],
          [
            7.102312,
            46.484985,
            1985.8
          ],
          [
            7.102315,
            46.485007,
            1987.2
          ],
          [
            7.102307,
            46.485027,
            1988.4
          ],
          [
            7.10229,
            46.485042,
            1990.0
          ],
          [
            7.102283,
            46.485062,
            1991.4
          ],
          [
            7.10227,
            46.485078,
            1992.8
          ],
          [
            7.10225,
            46.48509,
            1994.6
          ],
          [
            7.102233,
            46.485107,
            1996.2
          ],
          [
            7.102217,
            46.485122,
            1997.6
          ],
          [
            7.102202,
            46.485138,
            1999.0
          ],
          [
            7.102182,
            46.485152,
            2000.6
          ],
          [
            7.102155,
            46.48516,
            2002.4
          ],
          [
            7.102132,
            46.485177,
            2003.8
          ],
          [
            7.10212,
            46.485193,
            2005.0
          ],
          [
            7.102093,
            46.485208,
            2006.2
          ],
          [
            7.102072,
            46.485222,
            2007.4
          ],
          [
            7.102052,
            46.485238,
            2009.0
          ],
          [
            7.10202,
            46.48525,
            2010.4
          ],
          [
            7.101998,
            46.48526,
            2011.2
          ],
          [
            7.101975,
            46.48527,
            2012.2
          ],
          [
            7.101953,
            46.485282,
            2012.8
          ],
          [
            7.10193,
            46.485298,
            2013.6
          ],
          [
            7.101907,
            46.485308,
            2014.4
          ],
          [
            7.10188,
            46.485318,
            2015.4
          ],
          [
            7.101853,
            46.485337,
            2016.2
          ],
          [
            7.10183,
            46.48535,
            2017.0
          ],
          [
            7.101805,
            46.485362,
            2017.8
          ],
          [
            7.10178,
            46.485368,
            2019.0
          ],
          [
            7.101763,
            46.485388,
            2019.8
          ],
          [
            7.101748,
            46.485403,
            2021.0
          ],
          [
            7.101722,
            46.48542,
            2022.4
          ],
          [
            7.1017,
            46.48543,
            2023.6
          ],
          [
            7.101675,
            46.48544,
            2025.0
          ],
          [
            7.10165,
            46.485445,
            2026.0
          ],
          [
            7.101638,
            46.485462,
            2027.0
          ],
          [
            7.101615,
            46.485478,
            2028.2
          ],
          [
            7.101593,
            46.48549,
            2028.8
          ],
          [
            7.101573,
            46.485503,
            2030.0
          ],
          [
            7.101553,
            46.485517,
            2031.0
          ],
          [
            7.10153,
            46.485528,
            2032.4
          ],
          [
            7.101515,
            46.485545,
            2033.4
          ],
          [
            7.101497,
            46.48556,
            2034.0
          ],
          [
            7.101468,
            46.485573,
            2035.4
          ],
          [
            7.101443,
            46.485583,
            2036.4
          ],
          [
            7.10142,
            46.485602,
            2037.2
          ],
          [
            7.101402,
            46.485622,
            2038.0
          ],
          [
            7.101385,
            46.485638,
            2038.8
          ],
          [
            7.101375,
            46.485657,
            2040.0
          ],
          [
            7.101358,
            46.485677,
            2041.2
          ],
          [
            7.10134,
            46.485695,
            2042.6
          ],
          [
            7.10132,
            46.485708,
            2043.6
          ],
          [
            7.101307,
            46.485733,
            2045.4
          ],
          [
            7.101283,
            46.485753,
            2046.6
          ],
          [
            7.101263,
            46.485775,
            2048.0
          ],
          [
            7.10125,
            46.485795,
            2049.4
          ],
          [
            7.101223,
            46.485803,
            2050.2
          ],
          [
            7.10121,
            46.48582,
            2051.2
          ],
          [
            7.101183,
            46.48584,
            2052.8
          ],
          [
            7.101163,
            46.485855,
            2053.8
          ],
          [
            7.101143,
            46.485875,
            2054.4
          ],
          [
            7.101122,
            46.485893,
            2055.0
          ],
          [
            7.101093,
            46.485907,
            2056.0
          ],
          [
            7.101068,
            46.485917,
            2056.8
          ],
          [
            7.101043,
            46.485935,
            2057.8
          ],
          [
            7.10102,
            46.485955,
            2059.0
          ],
          [
            7.101,
            46.485973,
            2059.8
          ],
          [
            7.100982,
            46.485997,
            2060.8
          ],
          [
            7.100955,
            46.486012,
            2061.4
          ],
          [
            7.100927,
            46.486025,
            2061.8
          ],
          [
            7.100897,
            46.486043,
            2062.4
          ],
          [
            7.100873,
            46.486063,
            2063.0
          ],
          [
            7.100853,
            46.486085,
            2063.4
          ],
          [
            7.10083,
            46.486112,
            2063.6
          ],
          [
            7.100815,
            46.486137,
            2063.6
          ],
          [
            7.100798,
            46.486162,
            2063.4
          ],
          [
            7.10079,
            46.486192,
            2063.2
          ],
          [
            7.100773,
            46.48622,
            2062.6
          ],
          [
            7.100753,
            46.486252,
            2062.4
          ],
          [
            7.100728,
            46.486278,
            2062.0
          ],
          [
            7.100703,
            46.486303,
            2061.6
          ],
          [
            7.100692,
            46.486328,
            2061.2
          ],
          [
            7.100678,
            46.486345,
            2061.0
          ],
          [
            7.10066,
            46.486363,
            2061.2
          ],
          [
            7.100648,
            46.48638,
            2061.4
          ],
          [
            7.100628,
            46.4864,
            2061.6
          ],
          [
            7.100612,
            46.486422,
            2061.8
          ],
          [
            7.1006,
            46.486443,
            2062.2
          ],
          [
            7.100583,
            46.486463,
            2063.0
          ],
          [
            7.100562,
            46.486482,
            2064.0
          ],
          [
            7.100547,
            46.486498,
            2064.6
          ],
          [
            7.100533,
            46.48652,
            2065.4
          ],
          [
            7.100527,
            46.486543,
            2066.0
          ],
          [
            7.10052,
            46.486568,
            2066.6
          ],
          [
            7.10051,
            46.486595,
            2067.2
          ],
          [
            7.10051,
            46.486617,
            2067.4
          ],
          [
            7.100513,
            46.48664,
            2067.6
          ],
          [
            7.100513,
            46.486662,
            2067.8
          ],
          [
            7.10052,
            46.48669,
            2068.0
          ],
          [
            7.100527,
            46.486713,
            2068.0
          ],
          [
            7.100533,
            46.486732,
            2068.4
          ],
          [
            7.10053,
            46.486758,
            2068.8
          ],
          [
            7.100522,
            46.48678,
            2069.0
          ],
          [
            7.100502,
            46.486805,
            2069.4
          ],
          [
            7.10049,
            46.486832,
            2069.8
          ],
          [
            7.10048,
            46.48685,
            2070.6
          ],
          [
            7.100465,
            46.48687,
            2071.6
          ],
          [
            7.10045,
            46.486888,
            2072.4
          ],
          [
            7.100433,
            46.486908,
            2073.4
          ],
          [
            7.100408,
            46.486923,
            2074.6
          ],
          [
            7.100382,
            46.486937,
            2075.4
          ],
          [
            7.100368,
            46.486953,
            2075.8
          ],
          [
            7.100357,
            46.486972,
            2076.4
          ]
        ]
      }
    }
  ],
  "bbox": [
    7.099993,
    46.476425,
    7.104985,
    46.486972
  ]
}